fastlr/__init__.py
fastlr/_fastlr.cpython-313-x86_64-linux-gnu.so
fastlr/logreg.py
fastlr/utils.py
fastlr.libs/libarmadillo-b35ffa1e.so.12.6.6
fastlr.libs/libarpack-042921fd.so.2.1.0
fastlr.libs/libblas-fe34f726.so.3.8.0
fastlr.libs/libgfortran-8f1e9814.so.5.0.0
fastlr.libs/libgomp-870cb1d0.so.1.0.0
fastlr.libs/liblapack-31d7d384.so.3.8.0
fastlr.libs/libopenblas-r0-11edc3fa.3.15.so
fastlr.libs/libopenblaso-r0-d77a1985.3.15.so
fastlr.libs/libopenblasp-r0-59ffcd50.3.15.so
fastlr.libs/libquadmath-828275a7.so.0.0.0
fastlr.libs/libsatlas-6c1f674f.so.3.10
fastlr.libs/libsuperlu-17b63ae5.so.5.1
fastlr-0.1.0.dist-info/METADATA
fastlr-0.1.0.dist-info/WHEEL
fastlr-0.1.0.dist-info/RECORD
