Metadata-Version: 2.1
Name: fastlr
Version: 0.1.0
Summary: Fast logistic regression
Author-Email: jsr-p <jsr-p@sodas.ku.dk>
Classifier: License :: OSI Approved :: MIT License
Classifier: Programming Language :: Python :: 3
Classifier: Programming Language :: Python :: 3.11
Classifier: Programming Language :: Python :: 3.12
Classifier: Programming Language :: Python :: 3.13
Project-URL: Homepage, https://github.com/jsr-p/fastlr
Project-URL: Repository, https://github.com/jsr-p/fastlr
Requires-Python: >=3.11
Requires-Dist: numpy>=2.3.1
Requires-Dist: scipy>=1.15.0
